cdk_cloudformation_datadog_monitors_downtimeschedule/__init__.py
cdk_cloudformation_datadog_monitors_downtimeschedule/py.typed
cdk_cloudformation_datadog_monitors_downtimeschedule/_jsii/__init__.py
cdk_cloudformation_datadog_monitors_downtimeschedule/_jsii/datadog-monitors-downtimeschedule@1.0.0-alpha.7.jsii.tgz
cdk_cloudformation_datadog_monitors_downtimeschedule-1.0.0a7.dist-info/LICENSE
cdk_cloudformation_datadog_monitors_downtimeschedule-1.0.0a7.dist-info/METADATA
cdk_cloudformation_datadog_monitors_downtimeschedule-1.0.0a7.dist-info/WHEEL
cdk_cloudformation_datadog_monitors_downtimeschedule-1.0.0a7.dist-info/top_level.txt
cdk_cloudformation_datadog_monitors_downtimeschedule-1.0.0a7.dist-info/RECORD
